tabulatehelper
