Metadata-Version: 2.1
Name: tabulatehelper
Version: 0.0.7
Summary: Converts tabular data like Pandas dataframe to GitHub Flavored Markdown table (wrapper around tabulate module).
Home-page: https://github.com/kiwi0fruit/tabulatehelper
Author: Peter Zagubisalo
Author-email: peter.zagubisalo@gmail.com
License: MIT
Platform: UNKNOWN
Classifier: Development Status :: 3 - Alpha
Classifier: Intended Audience :: Developers
Classifier: Topic :: Software Development :: Build Tools
Classifier: License :: OSI Approved :: MIT License
Classifier: Programming Language :: Python :: 3
Classifier: Programming Language :: Python :: 3.6
Requires-Python: >=3.6
